chinese_calendar/__init__.py
chinese_calendar/constants.py
chinese_calendar/solar_terms.py
chinese_calendar/utils.py
chinese_calendar-1.9.2.dist-info/LICENSE
chinese_calendar-1.9.2.dist-info/METADATA
chinese_calendar-1.9.2.dist-info/WHEEL
chinese_calendar-1.9.2.dist-info/top_level.txt
chinese_calendar-1.9.2.dist-info/RECORD
