Metadata-Version: 2.1
Name: chinese_calendar
Version: 1.9.2
Summary: check if some day is holiday in China
Home-page: https://github.com/LKI/chinese-calendar
Author: Lirian Su
Author-email: liriansu@gmail.com
License: MIT License
Classifier: License :: OSI Approved :: MIT License
Classifier: Programming Language :: Python :: 3
Classifier: Programming Language :: Python :: 3.8
Classifier: Programming Language :: Python :: 3.9
Classifier: Programming Language :: Python :: 3.10
Classifier: Programming Language :: Python :: 3.11
Classifier: Programming Language :: Python :: 3.12
License-File: LICENSE
